<?xml version="1.0"?>
<opencv_storage>
<stage3>
  <maxWeakCount>12</maxWeakCount>
  <stageThreshold>-1.3563367128372192e+00</stageThreshold>
  <weakClassifiers>
    <_>
      <internalNodes>
        0 -1 5039073 1.5696851960456115e-06</internalNodes>
      <leafValues>
        -4.4262295961380005e-01 6.8186426162719727e-01</leafValues></_>
    <_>
      <internalNodes>
        0 -1 4185632 4.3530703806027304e-06</internalNodes>
      <leafValues>
        -3.3052074909210205e-01 4.5976817607879639e-01</leafValues></_>
    <_>
      <internalNodes>
        0 -1 3932206 -3.7043631076812744e-02</internalNodes>
      <leafValues>
        -9.2839074134826660e-01 1.6806246340274811e-01</leafValues></_>
    <_>
      <internalNodes>
        0 -1 3939446 1.0549703438300639e-04</internalNodes>
      <leafValues>
        -3.6473831534385681e-01 4.5202913880348206e-01</leafValues></_>
    <_>
      <internalNodes>
        0 -1 4530858 7.6117873191833496e-02</internalNodes>
      <leafValues>
        1.5926429629325867e-01 -8.4086662530899048e-01</leafValues></_>
    <_>
      <internalNodes>
        0 -1 6121209 3.7484682979993522e-04</internalNodes>
      <leafValues>
        -3.2791787385940552e-01 4.0687832236289978e-01</leafValues></_>
    <_>
      <internalNodes>
        0 -1 5467954 1.5644018276361749e-06</internalNodes>
      <leafValues>
        -3.7051638960838318e-01 3.6664363741874695e-01</leafValues></_>
    <_>
      <internalNodes>
        0 -1 4489623 -3.1277138739824295e-02</internalNodes>
      <leafValues>
        -8.7531286478042603e-01 1.3172735273838043e-01</leafValues></_>
    <_>
      <internalNodes>
        0 -1 3774906 1.8739295774139464e-04</internalNodes>
      <leafValues>
        -2.8354072570800781e-01 5.0155752897262573e-01</leafValues></_>
    <_>
      <internalNodes>
        0 -1 5572386 3.8436377508332953e-05</internalNodes>
      <leafValues>
        1.8220038712024689e-01 -9.4099628925323486e-01</leafValues></_>
    <_>
      <internalNodes>
        0 -1 7105572 5.9591711033135653e-04</internalNodes>
      <leafValues>
        -2.3934413492679596e-01 7.2709399461746216e-01</leafValues></_>
    <_>
      <internalNodes>
        0 -1 6314074 -1.0618072701618075e-04</internalNodes>
      <leafValues>
        6.6777420043945312e-01 -1.9228971004486084e-01</leafValues></_></weakClassifiers></stage3>
</opencv_storage>
